src/__init__.py
src/get_function_calling_schema.py
openai_func_parser-0.1.0.dist-info/METADATA
openai_func_parser-0.1.0.dist-info/WHEEL
openai_func_parser-0.1.0.dist-info/RECORD
