Metadata-Version: 2.1
Name: openai-func-parser
Version: 0.1.0
Summary: Transform Python function docstrings into JSON schemas compliant with OpenAI function calling protocols.
License: MIT
Author: Xiaotian Duan
Author-email: xduan7@gmail.com
Requires-Python: >=3.10,<4.0
Classifier: License :: OSI Approved :: MIT License
Classifier: Programming Language :: Python :: 3
Classifier: Programming Language :: Python :: 3.10
Classifier: Programming Language :: Python :: 3.11
Classifier: Programming Language :: Python :: 3.12
Requires-Dist: docstring-parser (>=0.15,<0.16)
Requires-Dist: openai (>=1.1.1,<2.0.0)
